{
  "atualizadoEm": "Atualizado em 14/07/2026, 03:36:58",
  "periodo": {
    "label": "Últimos 7 dias"
  },
  "clientes": [
    {
      "nome": "SOUZAGNERI",
      "seg": "—",
      "plano": "Ouro",
      "ig": "@souzagneri",
      "acc": "1599437730832316",
      "status": "ATIVO",
      "spend": 944.44,
      "impr": 81844,
      "reach": 39643,
      "clicks": 1578,
      "ctr": 1.928058,
      "cpc": 0.598504,
      "cpm": 11.539514,
      "freq": 2.064526,
      "linkClicks": 0,
      "pay": true,
      "camps": [
        {
          "n": "WHATS / 03.07.26 / WIFI / 100D",
          "spend": 795.57,
          "impr": 45028,
          "clicks": 990,
          "ctr": 2.198632,
          "cpc": 0.803606
        },
        {
          "n": "IG - PERFIL / 07.05 / TODOS / 30D",
          "spend": 148.87,
          "impr": 36816,
          "clicks": 588,
          "ctr": 1.597132,
          "cpc": 0.25318
        }
      ]
    },
    {
      "nome": "ODONTO CHUEH",
      "seg": "—",
      "plano": "Ouro",
      "ig": "@odontochueh",
      "acc": "776932710078790",
      "status": "ATIVO",
      "spend": 893.17,
      "impr": 134522,
      "reach": 49495,
      "clicks": 1230,
      "ctr": 0.914349,
      "cpc": 0.726154,
      "cpm": 6.639583,
      "freq": 2.717891,
      "linkClicks": 0,
      "pay": true,
      "camps": [
        {
          "n": "WHATS / 03.07.26 / WIFI / 110D",
          "spend": 753.25,
          "impr": 89861,
          "clicks": 732,
          "ctr": 0.814591,
          "cpc": 1.02903
        },
        {
          "n": "IG- PERFIL / 20.06 / todos / 25D",
          "spend": 139.92,
          "impr": 44661,
          "clicks": 498,
          "ctr": 1.115067,
          "cpc": 0.280964
        }
      ]
    },
    {
      "nome": "DENT-X",
      "seg": "—",
      "plano": "Start",
      "ig": "@dentxodontologia",
      "acc": "495685006882489",
      "status": "ATIVO",
      "spend": 753.67,
      "impr": 81583,
      "reach": 35091,
      "clicks": 933,
      "ctr": 1.143621,
      "cpc": 0.807792,
      "cpm": 9.238077,
      "freq": 2.324898,
      "linkClicks": 0,
      "pay": true,
      "camps": [
        {
          "n": "WHATS ORIGINAL  / 03.07  / +30 / 100D",
          "spend": 682.69,
          "impr": 60753,
          "clicks": 549,
          "ctr": 0.903659,
          "cpc": 1.243515
        },
        {
          "n": "IG-PERFIL / 09.02.26 / TODOS / 10D",
          "spend": 70.98,
          "impr": 20830,
          "clicks": 384,
          "ctr": 1.843495,
          "cpc": 0.184844
        }
      ]
    },
    {
      "nome": "Ortodonto",
      "seg": "—",
      "plano": "Start",
      "ig": "@ortodonto_se",
      "acc": "2046299446147904",
      "status": "ATIVO",
      "spend": 53.93,
      "impr": 18232,
      "reach": 15078,
      "clicks": 282,
      "ctr": 1.546731,
      "cpc": 0.191241,
      "cpm": 2.957986,
      "freq": 1.209179,
      "linkClicks": 0,
      "pay": true,
      "camps": [
        {
          "n": "IG- PERFIL / 22.05.26 / WIFI / 8D",
          "spend": 53.93,
          "impr": 18232,
          "clicks": 282,
          "ctr": 1.546731,
          "cpc": 0.191241
        }
      ]
    },
    {
      "nome": "I. CLÍNICO ESPECIALIZADO - Plano Prata",
      "seg": "—",
      "plano": "—",
      "ig": "—",
      "acc": "37012127715052483",
      "status": "ATIVO",
      "spend": 69.5,
      "impr": 12170,
      "reach": 8265,
      "clicks": 215,
      "ctr": 1.766639,
      "cpc": 0.323256,
      "cpm": 5.710764,
      "freq": 1.472474,
      "linkClicks": 0,
      "pay": true,
      "camps": [
        {
          "n": "IG ATA / 19.06 / Todos / 5KM / 10D",
          "spend": 69.5,
          "impr": 12170,
          "clicks": 215,
          "ctr": 1.766639,
          "cpc": 0.323256
        }
      ]
    },
    {
      "nome": "AMAR - Plano Start",
      "seg": "—",
      "plano": "Start",
      "ig": "—",
      "acc": "312676821930863",
      "status": "DORMENTE",
      "spend": 0,
      "impr": 0,
      "reach": 0,
      "clicks": 0,
      "ctr": 0,
      "cpc": 0,
      "cpm": 0,
      "freq": 0,
      "linkClicks": 0,
      "pay": true,
      "camps": []
    },
    {
      "nome": "ÓTICA ÓPTIMA - Plano Prata",
      "seg": "—",
      "plano": "—",
      "ig": "—",
      "acc": "969933572256897",
      "status": "ATIVO",
      "spend": 315.89,
      "impr": 34487,
      "reach": 24089,
      "clicks": 449,
      "ctr": 1.30194,
      "cpc": 0.703541,
      "cpm": 9.159683,
      "freq": 1.431649,
      "linkClicks": 0,
      "pay": true,
      "camps": [
        {
          "n": "WHATS / 07.07 / TODOS / 35D",
          "spend": 230.99,
          "impr": 11992,
          "clicks": 136,
          "ctr": 1.134089,
          "cpc": 1.698456
        },
        {
          "n": "IG - PERFIL / 06.07 / TODOS / 10D",
          "spend": 70.12,
          "impr": 21875,
          "clicks": 310,
          "ctr": 1.417143,
          "cpc": 0.226194
        },
        {
          "n": "WHATS ENG / 11.06 / TODOS / 35D",
          "spend": 14.78,
          "impr": 620,
          "clicks": 3,
          "ctr": 0.483871,
          "cpc": 4.926667
        }
      ]
    },
    {
      "nome": "ATA - 05",
      "seg": "—",
      "plano": "—",
      "ig": "@ata.deco",
      "acc": "37012127715052483",
      "status": "ATIVO",
      "spend": 69.5,
      "impr": 12170,
      "reach": 8265,
      "clicks": 215,
      "ctr": 1.766639,
      "cpc": 0.323256,
      "cpm": 5.710764,
      "freq": 1.472474,
      "linkClicks": 0,
      "pay": true,
      "camps": [
        {
          "n": "IG ATA / 19.06 / Todos / 5KM / 10D",
          "spend": 69.5,
          "impr": 12170,
          "clicks": 215,
          "ctr": 1.766639,
          "cpc": 0.323256
        }
      ]
    },
    {
      "nome": "CAFEÍNA URBANA ARQUITETURA",
      "seg": "Arquitetura",
      "plano": "—",
      "ig": "—",
      "acc": "973988312272175",
      "status": "ATIVO",
      "spend": 75.4,
      "impr": 13971,
      "reach": 12520,
      "clicks": 254,
      "ctr": 1.818052,
      "cpc": 0.29685,
      "cpm": 5.396894,
      "freq": 1.115895,
      "linkClicks": 0,
      "pay": true,
      "camps": [
        {
          "n": "IG GERAL / 16.06 / 25+ / TODOS / 10D",
          "spend": 75.4,
          "impr": 13971,
          "clicks": 254,
          "ctr": 1.818052,
          "cpc": 0.29685
        }
      ]
    },
    {
      "nome": "LOJA REIS",
      "seg": "—",
      "plano": "—",
      "ig": "—",
      "acc": "—",
      "status": "SEM_CONTA",
      "spend": 0,
      "impr": 0,
      "reach": 0,
      "clicks": 0,
      "ctr": 0,
      "cpc": 0,
      "cpm": 0,
      "freq": 0,
      "linkClicks": 0,
      "pay": true,
      "camps": []
    },
    {
      "nome": "RR SPA MOBILE - Plano Start",
      "seg": "—",
      "plano": "Start",
      "ig": "—",
      "acc": "877905779872333",
      "status": "ATIVO",
      "spend": 292.42,
      "impr": 21398,
      "reach": 14786,
      "clicks": 553,
      "ctr": 2.584354,
      "cpc": 0.528788,
      "cpm": 13.665763,
      "freq": 1.44718,
      "linkClicks": 0,
      "pay": true,
      "camps": [
        {
          "n": "WHATS / 22.04 / WIFI / 25 - 60  / 24 D",
          "spend": 173.62,
          "impr": 10790,
          "clicks": 243,
          "ctr": 2.252085,
          "cpc": 0.714486
        },
        {
          "n": "CURSO RR / 03.07 / TODOS / 15D",
          "spend": 71.56,
          "impr": 3576,
          "clicks": 36,
          "ctr": 1.006711,
          "cpc": 1.987778
        },
        {
          "n": "IG-PERFIL / 31.01 / todos / 25+ / 7D",
          "spend": 47.24,
          "impr": 7032,
          "clicks": 274,
          "ctr": 3.896473,
          "cpc": 0.172409
        }
      ]
    },
    {
      "nome": "GERAÇÃO DE MINAS - 05",
      "seg": "—",
      "plano": "Start",
      "ig": "@geracaodeminassp",
      "acc": "3517126421796226",
      "status": "ATIVO",
      "spend": 360.83,
      "impr": 33036,
      "reach": 26457,
      "clicks": 2396,
      "ctr": 7.252694,
      "cpc": 0.150597,
      "cpm": 10.922327,
      "freq": 1.248668,
      "linkClicks": 0,
      "pay": true,
      "camps": [
        {
          "n": "PERFIL / 04.07  / TODOS / 18+ / 50D",
          "spend": 360.83,
          "impr": 33036,
          "clicks": 2396,
          "ctr": 7.252694,
          "cpc": 0.150597
        }
      ]
    },
    {
      "nome": "BACACIO AÇAI",
      "seg": "Alimentação",
      "plano": "—",
      "ig": "—",
      "acc": "2117547009034350",
      "status": "DORMENTE",
      "spend": 0,
      "impr": 0,
      "reach": 0,
      "clicks": 0,
      "ctr": 0,
      "cpc": 0,
      "cpm": 0,
      "freq": 0,
      "linkClicks": 0,
      "pay": true,
      "camps": []
    },
    {
      "nome": "TENORIOS - 10",
      "seg": "—",
      "plano": "Start",
      "ig": "@tenoriosburger.saoluis",
      "acc": "730924665516463",
      "status": "ATIVO",
      "spend": 89.04,
      "impr": 21054,
      "reach": 12767,
      "clicks": 301,
      "ctr": 1.429657,
      "cpc": 0.295814,
      "cpm": 4.229125,
      "freq": 1.649095,
      "linkClicks": 0,
      "pay": true,
      "camps": [
        {
          "n": "C. WEB JULHO / 01.07 - 30.07  / WIFI / 4KM / 400T",
          "spend": 89.04,
          "impr": 21054,
          "clicks": 301,
          "ctr": 1.429657,
          "cpc": 0.295814
        }
      ]
    },
    {
      "nome": "UNIÃO DE MINAS",
      "seg": "—",
      "plano": "Start",
      "ig": "@barerestaurante.uniaodeminas",
      "acc": "1076173037436485",
      "status": "ATIVO",
      "spend": 70,
      "impr": 16657,
      "reach": 10792,
      "clicks": 294,
      "ctr": 1.765024,
      "cpc": 0.238095,
      "cpm": 4.202437,
      "freq": 1.543458,
      "linkClicks": 0,
      "pay": true,
      "camps": [
        {
          "n": "IG PERFIL / 05.05.26 / TODOS / 10D",
          "spend": 70,
          "impr": 16657,
          "clicks": 294,
          "ctr": 1.765024,
          "cpc": 0.238095
        }
      ]
    },
    {
      "nome": "PADARIA RAINHA DA SUL - 05",
      "seg": "—",
      "plano": "Start",
      "ig": "—",
      "acc": "892357802999114",
      "status": "ATIVO",
      "spend": 143.31,
      "impr": 20078,
      "reach": 15361,
      "clicks": 511,
      "ctr": 2.545074,
      "cpc": 0.28045,
      "cpm": 7.137663,
      "freq": 1.307076,
      "linkClicks": 0,
      "pay": true,
      "camps": [
        {
          "n": "IG-perfil / 20.01.26 / todos / 20D",
          "spend": 143.31,
          "impr": 20078,
          "clicks": 511,
          "ctr": 2.545074,
          "cpc": 0.28045
        }
      ]
    },
    {
      "nome": "TAPIOCA ALAGOANA - 10",
      "seg": "—",
      "plano": "Start",
      "ig": "@tapiocalagoana",
      "acc": "—",
      "status": "SEM_CONTA",
      "spend": 0,
      "impr": 0,
      "reach": 0,
      "clicks": 0,
      "ctr": 0,
      "cpc": 0,
      "cpm": 0,
      "freq": 0,
      "linkClicks": 0,
      "pay": true,
      "camps": []
    },
    {
      "nome": "SERVEMEI - Plano Start",
      "seg": "—",
      "plano": "Start",
      "ig": "—",
      "acc": "2416703108676525",
      "status": "ATIVO",
      "spend": 620.86,
      "impr": 41362,
      "reach": 30585,
      "clicks": 1867,
      "ctr": 4.513805,
      "cpc": 0.332544,
      "cpm": 15.010396,
      "freq": 1.352362,
      "linkClicks": 0,
      "pay": true,
      "camps": [
        {
          "n": "WHATS / 04.07.26 / TODOS / 110D",
          "spend": 538.23,
          "impr": 35674,
          "clicks": 1141,
          "ctr": 3.198408,
          "cpc": 0.471718
        },
        {
          "n": "IG-PERFIL / 21.01.26 / WIFI / BR-20_50 / 15D",
          "spend": 82.63,
          "impr": 5688,
          "clicks": 726,
          "ctr": 12.763713,
          "cpc": 0.113815
        }
      ]
    },
    {
      "nome": "MASTER CLEAN PRO AJU",
      "seg": "Produtos de Limpeza",
      "plano": "—",
      "ig": "—",
      "acc": "1499544194883369",
      "status": "DORMENTE",
      "spend": 0,
      "impr": 0,
      "reach": 0,
      "clicks": 0,
      "ctr": 0,
      "cpc": 0,
      "cpm": 0,
      "freq": 0,
      "linkClicks": 0,
      "pay": true,
      "camps": []
    },
    {
      "nome": "CHACARA  DA SERRA - Plano Start",
      "seg": "—",
      "plano": "Start",
      "ig": "—",
      "acc": "1343108897056888",
      "status": "ATIVO",
      "spend": 207.42,
      "impr": 43407,
      "reach": 31871,
      "clicks": 1209,
      "ctr": 2.785265,
      "cpc": 0.171563,
      "cpm": 4.778492,
      "freq": 1.361959,
      "linkClicks": 0,
      "pay": true,
      "camps": [
        {
          "n": "IG GERAL / 15.06 / TODOS / 10 D",
          "spend": 136.1,
          "impr": 22711,
          "clicks": 879,
          "ctr": 3.870371,
          "cpc": 0.154835
        },
        {
          "n": "WHATS / 10.07 / TODOS / 20D",
          "spend": 71.32,
          "impr": 20696,
          "clicks": 330,
          "ctr": 1.594511,
          "cpc": 0.216121
        }
      ]
    },
    {
      "nome": "ADRIANO DIAS POSITIVO - 10",
      "seg": "—",
      "plano": "—",
      "ig": "@adrianodiaspositivo",
      "acc": "—",
      "status": "SEM_CONTA",
      "spend": 0,
      "impr": 0,
      "reach": 0,
      "clicks": 0,
      "ctr": 0,
      "cpc": 0,
      "cpm": 0,
      "freq": 0,
      "linkClicks": 0,
      "pay": true,
      "camps": []
    },
    {
      "nome": "PARCÃO PET - Plano Start",
      "seg": "—",
      "plano": "Start",
      "ig": "—",
      "acc": "—",
      "status": "SEM_CONTA",
      "spend": 0,
      "impr": 0,
      "reach": 0,
      "clicks": 0,
      "ctr": 0,
      "cpc": 0,
      "cpm": 0,
      "freq": 0,
      "linkClicks": 0,
      "pay": true,
      "camps": []
    },
    {
      "nome": "LUCKS LANCHES -10",
      "seg": "—",
      "plano": "Start",
      "ig": "@luckslanches",
      "acc": "724989819654241",
      "status": "ATIVO",
      "spend": 90.41,
      "impr": 17849,
      "reach": 13806,
      "clicks": 344,
      "ctr": 1.927279,
      "cpc": 0.26282,
      "cpm": 5.06527,
      "freq": 1.292844,
      "linkClicks": 0,
      "pay": true,
      "camps": [
        {
          "n": "IG PERFIL JULHO / WIFI / 20_60 / 18H_01H / 400T",
          "spend": 90.41,
          "impr": 17849,
          "clicks": 344,
          "ctr": 1.927279,
          "cpc": 0.26282
        }
      ]
    },
    {
      "nome": "BRENO RODRIGUES - Plano Start",
      "seg": "—",
      "plano": "Start",
      "ig": "—",
      "acc": "952366480052425",
      "status": "DORMENTE",
      "spend": 0,
      "impr": 0,
      "reach": 0,
      "clicks": 0,
      "ctr": 0,
      "cpc": 0,
      "cpm": 0,
      "freq": 0,
      "linkClicks": 0,
      "pay": true,
      "camps": []
    },
    {
      "nome": "VILLA MACARRONE",
      "seg": "—",
      "plano": "Start",
      "ig": "@villamacarroneoficial",
      "acc": "—",
      "status": "SEM_CONTA",
      "spend": 0,
      "impr": 0,
      "reach": 0,
      "clicks": 0,
      "ctr": 0,
      "cpc": 0,
      "cpm": 0,
      "freq": 0,
      "linkClicks": 0,
      "pay": true,
      "camps": []
    }
  ]
}